{
    "Gender": 0,
    "Parents": {
        "Father": 4,
        "Mother": 35,
        "Similarity": 0.99,
        "SkinSimilarity": 0.7000000000000001
    },
    "Features": [
        0,
        0,
        0,
        0,
        0,
        0,
        0,
        0,
        0,
        0,
        0,
        0,
        0,
        0,
        0,
        0,
        0,
        0,
        0,
        0
    ],
    "Appearance": [
        {
            "Value": 255,
            "Opacity": 1
        },
        {
            "Value": 255,
            "Opacity": 1
        },
        {
            "Value": 255,
            "Opacity": 1
        },
        {
            "Value": 255,
            "Opacity": 1
        },
        {
            "Value": 255,
            "Opacity": 1
        },
        {
            "Value": 255,
            "Opacity": 1
        },
        {
            "Value": 255,
            "Opacity": 1
        },
        {
            "Value": 255,
            "Opacity": 1
        },
        {
            "Value": 255,
            "Opacity": 1
        },
        {
            "Value": 255,
            "Opacity": 1
        },
        {
            "Value": 255,
            "Opacity": 1
        }
    ],
    "Hair": {
        "Hair": 2,
        "Color": 0,
        "HighlightColor": 0
    },
    "EyebrowColor": 0,
    "BeardColor": 0,
    "EyeColor": 0,
    "BlushColor": 0,
    "LipstickColor": 0,
    "ChestHairColor": 0
}